jet_files/list_commits.py
jet_files/revert.py
jet_files/init.py
jet_files/merge.py
jet_files/conflicts.py
jet_files/branch.py
jet_files/pull.py
jet_files/stash.py
jet_files/commit_changeset.py
jet_files/help_text.py
jet_files/push.py
jet_files/setup.py
jet_files/diff.py
jet_files/local_tests.py
jet_files/jet.py
jet_files/hook.py
jet_files/helper_functions.py
jet_files/status.py
jet_files/add.py
jet_files/login.py
jet_files/__init__.py
jet_files/tests/__init__.py
jet_files/tests/merge/__init__.py
jet_files/tests/merge/8/parent.py
jet_files/tests/merge/8/file2.py
jet_files/tests/merge/8/expected_result.py
jet_files/tests/merge/8/__init__.py
jet_files/tests/merge/8/file1.py
jet_files/tests/merge/5/parent.py
jet_files/tests/merge/5/file2.py
jet_files/tests/merge/5/expected_result.py
jet_files/tests/merge/5/__init__.py
jet_files/tests/merge/5/file1.py
jet_files/tests/merge/6/parent.py
jet_files/tests/merge/6/file2.py
jet_files/tests/merge/6/expected_result.py
jet_files/tests/merge/6/__init__.py
jet_files/tests/merge/6/file1.py
jet_files/tests/merge/10/parent.py
jet_files/tests/merge/10/file2.py
jet_files/tests/merge/10/expected_result.py
jet_files/tests/merge/10/__init__.py
jet_files/tests/merge/10/file1.py
jet_files/tests/merge/3/parent.py
jet_files/tests/merge/3/file2.py
jet_files/tests/merge/3/expected_result.py
jet_files/tests/merge/3/__init__.py
jet_files/tests/merge/3/file1.py
jet_files/tests/merge/9/parent.py
jet_files/tests/merge/9/file2.py
jet_files/tests/merge/9/expected_result.py
jet_files/tests/merge/9/__init__.py
jet_files/tests/merge/9/file1.py
jet_files/tests/merge/13/parent.py
jet_files/tests/merge/13/file2.py
jet_files/tests/merge/13/expected_result.py
jet_files/tests/merge/13/__init__.py
jet_files/tests/merge/13/file1.py
jet_files/tests/merge/2/parent.py
jet_files/tests/merge/2/file2.py
jet_files/tests/merge/2/expected_result.py
jet_files/tests/merge/2/__init__.py
jet-0.3.8.dist-info/WHEEL
jet-0.3.8.dist-info/top_level.txt
jet-0.3.8.dist-info/DESCRIPTION.rst
jet-0.3.8.dist-info/RECORD
jet-0.3.8.dist-info/METADATA
jet-0.3.8.dist-info/metadata.json
jet-0.3.8.dist-info/entry_points.txt
