Metadata-Version: 2.0
Name: jet
Version: 0.3.8
Summary: A simple to use, yet powerful version control system
Home-page: https://github.com/entangly/jet/
Author: Connor Swain
Author-email: connor@bradingsoftware.co.uk
License: MIT
Keywords: version control jet
Platform: UNKNOWN
Classifier: Development Status :: 3 - Alpha
Classifier: Intended Audience :: Developers
Classifier: Topic :: Software Development :: Version Control
Classifier: License :: OSI Approved :: MIT License
Classifier: Programming Language :: Python :: 2.7
Requires-Dist: requests
